RCJRVision/RCJRVision.py
RCJRVision/__init__.py
RCJRVision/contours.py
RCJRVision/msgs.py
RCJRVision/params.py
RCJRVision/saveSampleContours.py
RCJRVision-1.5.dist-info/LICENSE
RCJRVision-1.5.dist-info/METADATA
RCJRVision-1.5.dist-info/WHEEL
RCJRVision-1.5.dist-info/top_level.txt
RCJRVision-1.5.dist-info/RECORD
