Metadata-Version: 2.1
Name: RCJRVision
Version: 1.5
Summary: A fast and simple image processing method to detect H S U victims in rescue maze
Home-page: https://github.com/mhmmdshirazi/RCJRVision
Author: Mohammad Mahdi Shirazi
Author-email: mhmmdshirazi@gmail.com
License: UNKNOWN
Platform: UNKNOWN
Classifier: Development Status :: 4 - Beta
Classifier: Intended Audience :: Developers
Classifier: Natural Language :: English
Classifier: License :: OSI Approved :: MIT License
Classifier: Operating System :: OS Independent
Classifier: Programming Language :: Python :: 3.5
Classifier: Programming Language :: Python :: 3.6
Classifier: Programming Language :: Python :: 3.7
Classifier: Programming Language :: Python :: 3.8
Requires-Python: >=3.5, <4
Requires-Dist: opencv-python (>=4.1.2.0)
Requires-Dist: opencv-python-headless (>=4.2.0)
Requires-Dist: numpy (>=1.9.0)
